{
  "app": {
    "[project]/app/_not-found/page": [
      "static/media/caa3a2e1cccd8315-s.p.853070df.woff2",
      "static/media/797e433ab948586e-s.p.dbea232f.woff2"
    ],
    "[project]/app/admin/ai-test/page": [
      "static/media/caa3a2e1cccd8315-s.p.853070df.woff2",
      "static/media/797e433ab948586e-s.p.dbea232f.woff2"
    ],
    "[project]/app/admin/debug/page": [
      "static/media/caa3a2e1cccd8315-s.p.853070df.woff2",
      "static/media/797e433ab948586e-s.p.dbea232f.woff2"
    ],
    "[project]/app/admin/emergency-email-fix/page": [
      "static/media/caa3a2e1cccd8315-s.p.853070df.woff2",
      "static/media/797e433ab948586e-s.p.dbea232f.woff2"
    ],
    "[project]/app/admin/find-user/page": [
      "static/media/caa3a2e1cccd8315-s.p.853070df.woff2",
      "static/media/797e433ab948586e-s.p.dbea232f.woff2"
    ],
    "[project]/app/admin/franchise-setup/page": [
      "static/media/caa3a2e1cccd8315-s.p.853070df.woff2",
      "static/media/797e433ab948586e-s.p.dbea232f.woff2"
    ],
    "[project]/app/admin/franchise/page": [
      "static/media/caa3a2e1cccd8315-s.p.853070df.woff2",
      "static/media/797e433ab948586e-s.p.dbea232f.woff2"
    ],
    "[project]/app/admin/login/page": [
      "static/media/caa3a2e1cccd8315-s.p.853070df.woff2",
      "static/media/797e433ab948586e-s.p.dbea232f.woff2"
    ],
    "[project]/app/admin/monitoring/page": [
      "static/media/caa3a2e1cccd8315-s.p.853070df.woff2",
      "static/media/797e433ab948586e-s.p.dbea232f.woff2"
    ],
    "[project]/app/admin/page": [
      "static/media/caa3a2e1cccd8315-s.p.853070df.woff2",
      "static/media/797e433ab948586e-s.p.dbea232f.woff2"
    ],
    "[project]/app/admin/utils/cleanup-auth/page": [
      "static/media/caa3a2e1cccd8315-s.p.853070df.woff2",
      "static/media/797e433ab948586e-s.p.dbea232f.woff2"
    ],
    "[project]/app/admin/utils/create-test-profile/page": [
      "static/media/caa3a2e1cccd8315-s.p.853070df.woff2",
      "static/media/797e433ab948586e-s.p.dbea232f.woff2"
    ],
    "[project]/app/admin/utils/debug-users/page": [
      "static/media/caa3a2e1cccd8315-s.p.853070df.woff2",
      "static/media/797e433ab948586e-s.p.dbea232f.woff2"
    ],
    "[project]/app/admin/utils/delete-orphaned-users/page": [
      "static/media/caa3a2e1cccd8315-s.p.853070df.woff2",
      "static/media/797e433ab948586e-s.p.dbea232f.woff2"
    ],
    "[project]/app/admin/utils/init-mock-user/page": [
      "static/media/caa3a2e1cccd8315-s.p.853070df.woff2",
      "static/media/797e433ab948586e-s.p.dbea232f.woff2"
    ],
    "[project]/app/admin/utils/reset-david/page": [
      "static/media/caa3a2e1cccd8315-s.p.853070df.woff2",
      "static/media/797e433ab948586e-s.p.dbea232f.woff2"
    ],
    "[project]/app/admin/wallet-pass-update/page": [
      "static/media/caa3a2e1cccd8315-s.p.853070df.woff2",
      "static/media/797e433ab948586e-s.p.dbea232f.woff2"
    ],
    "[project]/app/auth/error/page": [
      "static/media/caa3a2e1cccd8315-s.p.853070df.woff2",
      "static/media/797e433ab948586e-s.p.dbea232f.woff2"
    ],
    "[project]/app/auth/forgot-password/page": [
      "static/media/caa3a2e1cccd8315-s.p.853070df.woff2",
      "static/media/797e433ab948586e-s.p.dbea232f.woff2"
    ],
    "[project]/app/auth/login/page": [
      "static/media/caa3a2e1cccd8315-s.p.853070df.woff2",
      "static/media/797e433ab948586e-s.p.dbea232f.woff2"
    ],
    "[project]/app/auth/sign-up-success/page": [
      "static/media/caa3a2e1cccd8315-s.p.853070df.woff2",
      "static/media/797e433ab948586e-s.p.dbea232f.woff2"
    ],
    "[project]/app/auth/sign-up/page": [
      "static/media/caa3a2e1cccd8315-s.p.853070df.woff2",
      "static/media/797e433ab948586e-s.p.dbea232f.woff2"
    ],
    "[project]/app/auth/update-password/page": [
      "static/media/caa3a2e1cccd8315-s.p.853070df.woff2",
      "static/media/797e433ab948586e-s.p.dbea232f.woff2"
    ],
    "[project]/app/business/dashboard/page": [
      "static/media/caa3a2e1cccd8315-s.p.853070df.woff2",
      "static/media/797e433ab948586e-s.p.dbea232f.woff2"
    ],
    "[project]/app/business/page": [
      "static/media/caa3a2e1cccd8315-s.p.853070df.woff2",
      "static/media/797e433ab948586e-s.p.dbea232f.woff2"
    ],
    "[project]/app/coming-soon/page": [
      "static/media/caa3a2e1cccd8315-s.p.853070df.woff2",
      "static/media/797e433ab948586e-s.p.dbea232f.woff2"
    ],
    "[project]/app/dashboard/action-items/page": [
      "static/media/caa3a2e1cccd8315-s.p.853070df.woff2",
      "static/media/797e433ab948586e-s.p.dbea232f.woff2"
    ],
    "[project]/app/dashboard/analytics/page": [
      "static/media/caa3a2e1cccd8315-s.p.853070df.woff2",
      "static/media/797e433ab948586e-s.p.dbea232f.woff2"
    ],
    "[project]/app/dashboard/business/page": [
      "static/media/caa3a2e1cccd8315-s.p.853070df.woff2",
      "static/media/797e433ab948586e-s.p.dbea232f.woff2"
    ],
    "[project]/app/dashboard/debug-subscription/page": [
      "static/media/caa3a2e1cccd8315-s.p.853070df.woff2",
      "static/media/797e433ab948586e-s.p.dbea232f.woff2"
    ],
    "[project]/app/dashboard/events/page": [
      "static/media/caa3a2e1cccd8315-s.p.853070df.woff2",
      "static/media/797e433ab948586e-s.p.dbea232f.woff2"
    ],
    "[project]/app/dashboard/files/page": [
      "static/media/caa3a2e1cccd8315-s.p.853070df.woff2",
      "static/media/797e433ab948586e-s.p.dbea232f.woff2"
    ],
    "[project]/app/dashboard/loyalty/page": [
      "static/media/caa3a2e1cccd8315-s.p.853070df.woff2",
      "static/media/797e433ab948586e-s.p.dbea232f.woff2"
    ],
    "[project]/app/dashboard/notifications/page": [
      "static/media/caa3a2e1cccd8315-s.p.853070df.woff2",
      "static/media/797e433ab948586e-s.p.dbea232f.woff2"
    ],
    "[project]/app/dashboard/offers/page": [
      "static/media/caa3a2e1cccd8315-s.p.853070df.woff2",
      "static/media/797e433ab948586e-s.p.dbea232f.woff2"
    ],
    "[project]/app/dashboard/page": [
      "static/media/caa3a2e1cccd8315-s.p.853070df.woff2",
      "static/media/797e433ab948586e-s.p.dbea232f.woff2"
    ],
    "[project]/app/dashboard/personal/page": [
      "static/media/caa3a2e1cccd8315-s.p.853070df.woff2",
      "static/media/797e433ab948586e-s.p.dbea232f.woff2"
    ],
    "[project]/app/dashboard/profile/page": [
      "static/media/caa3a2e1cccd8315-s.p.853070df.woff2",
      "static/media/797e433ab948586e-s.p.dbea232f.woff2"
    ],
    "[project]/app/dashboard/profile/preview/page": [
      "static/media/caa3a2e1cccd8315-s.p.853070df.woff2",
      "static/media/797e433ab948586e-s.p.dbea232f.woff2"
    ],
    "[project]/app/dashboard/referrals/page": [
      "static/media/caa3a2e1cccd8315-s.p.853070df.woff2",
      "static/media/797e433ab948586e-s.p.dbea232f.woff2"
    ],
    "[project]/app/dashboard/secret-menu/page": [
      "static/media/caa3a2e1cccd8315-s.p.853070df.woff2",
      "static/media/797e433ab948586e-s.p.dbea232f.woff2"
    ],
    "[project]/app/dashboard/settings/page": [
      "static/media/caa3a2e1cccd8315-s.p.853070df.woff2",
      "static/media/797e433ab948586e-s.p.dbea232f.woff2"
    ],
    "[project]/app/dashboard/social-wizard/page": [
      "static/media/caa3a2e1cccd8315-s.p.853070df.woff2",
      "static/media/797e433ab948586e-s.p.dbea232f.woff2"
    ],
    "[project]/app/dashboard/support/page": [
      "static/media/caa3a2e1cccd8315-s.p.853070df.woff2",
      "static/media/797e433ab948586e-s.p.dbea232f.woff2"
    ],
    "[project]/app/debug-image-editor/page": [
      "static/media/caa3a2e1cccd8315-s.p.853070df.woff2",
      "static/media/797e433ab948586e-s.p.dbea232f.woff2"
    ],
    "[project]/app/debug-supabase/page": [
      "static/media/caa3a2e1cccd8315-s.p.853070df.woff2",
      "static/media/797e433ab948586e-s.p.dbea232f.woff2"
    ],
    "[project]/app/embed/chat/page": [
      "static/media/caa3a2e1cccd8315-s.p.853070df.woff2",
      "static/media/797e433ab948586e-s.p.dbea232f.woff2"
    ],
    "[project]/app/install-wallet-pass/page": [
      "static/media/caa3a2e1cccd8315-s.p.853070df.woff2",
      "static/media/797e433ab948586e-s.p.dbea232f.woff2"
    ],
    "[project]/app/intent/[...params]/page": [
      "static/media/caa3a2e1cccd8315-s.p.853070df.woff2",
      "static/media/797e433ab948586e-s.p.dbea232f.woff2"
    ],
    "[project]/app/intent/[code]/page": [
      "static/media/caa3a2e1cccd8315-s.p.853070df.woff2",
      "static/media/797e433ab948586e-s.p.dbea232f.woff2"
    ],
    "[project]/app/intent/page": [
      "static/media/caa3a2e1cccd8315-s.p.853070df.woff2",
      "static/media/797e433ab948586e-s.p.dbea232f.woff2"
    ],
    "[project]/app/offline/page": [
      "static/media/caa3a2e1cccd8315-s.p.853070df.woff2",
      "static/media/797e433ab948586e-s.p.dbea232f.woff2"
    ],
    "[project]/app/onboarding/page": [
      "static/media/caa3a2e1cccd8315-s.p.853070df.woff2",
      "static/media/797e433ab948586e-s.p.dbea232f.woff2"
    ],
    "[project]/app/onboarding/success/page": [
      "static/media/caa3a2e1cccd8315-s.p.853070df.woff2",
      "static/media/797e433ab948586e-s.p.dbea232f.woff2"
    ],
    "[project]/app/page": [
      "static/media/caa3a2e1cccd8315-s.p.853070df.woff2",
      "static/media/797e433ab948586e-s.p.dbea232f.woff2"
    ],
    "[project]/app/phase2-gate/page": [
      "static/media/caa3a2e1cccd8315-s.p.853070df.woff2",
      "static/media/797e433ab948586e-s.p.dbea232f.woff2"
    ],
    "[project]/app/privacy-policy/page": [
      "static/media/caa3a2e1cccd8315-s.p.853070df.woff2",
      "static/media/797e433ab948586e-s.p.dbea232f.woff2"
    ],
    "[project]/app/protected/page": [
      "static/media/caa3a2e1cccd8315-s.p.853070df.woff2",
      "static/media/797e433ab948586e-s.p.dbea232f.woff2"
    ],
    "[project]/app/simulate-wallet-pass/page": [
      "static/media/caa3a2e1cccd8315-s.p.853070df.woff2",
      "static/media/797e433ab948586e-s.p.dbea232f.woff2"
    ],
    "[project]/app/terms-of-service/page": [
      "static/media/caa3a2e1cccd8315-s.p.853070df.woff2",
      "static/media/797e433ab948586e-s.p.dbea232f.woff2"
    ],
    "[project]/app/test-ai/page": [
      "static/media/caa3a2e1cccd8315-s.p.853070df.woff2",
      "static/media/797e433ab948586e-s.p.dbea232f.woff2"
    ],
    "[project]/app/test-qr-scroll/page": [
      "static/media/caa3a2e1cccd8315-s.p.853070df.woff2",
      "static/media/797e433ab948586e-s.p.dbea232f.woff2"
    ],
    "[project]/app/user/badges/page": [
      "static/media/caa3a2e1cccd8315-s.p.853070df.woff2",
      "static/media/797e433ab948586e-s.p.dbea232f.woff2"
    ],
    "[project]/app/user/business/[slug]/page": [
      "static/media/caa3a2e1cccd8315-s.p.853070df.woff2",
      "static/media/797e433ab948586e-s.p.dbea232f.woff2"
    ],
    "[project]/app/user/chat/page": [
      "static/media/caa3a2e1cccd8315-s.p.853070df.woff2",
      "static/media/797e433ab948586e-s.p.dbea232f.woff2"
    ],
    "[project]/app/user/dashboard/page": [
      "static/media/caa3a2e1cccd8315-s.p.853070df.woff2",
      "static/media/797e433ab948586e-s.p.dbea232f.woff2"
    ],
    "[project]/app/user/discover/page": [
      "static/media/caa3a2e1cccd8315-s.p.853070df.woff2",
      "static/media/797e433ab948586e-s.p.dbea232f.woff2"
    ],
    "[project]/app/user/events/page": [
      "static/media/caa3a2e1cccd8315-s.p.853070df.woff2",
      "static/media/797e433ab948586e-s.p.dbea232f.woff2"
    ],
    "[project]/app/user/how-it-works/page": [
      "static/media/caa3a2e1cccd8315-s.p.853070df.woff2",
      "static/media/797e433ab948586e-s.p.dbea232f.woff2"
    ],
    "[project]/app/user/offers/page": [
      "static/media/caa3a2e1cccd8315-s.p.853070df.woff2",
      "static/media/797e433ab948586e-s.p.dbea232f.woff2"
    ],
    "[project]/app/user/page": [
      "static/media/caa3a2e1cccd8315-s.p.853070df.woff2",
      "static/media/797e433ab948586e-s.p.dbea232f.woff2"
    ],
    "[project]/app/user/saved/page": [
      "static/media/caa3a2e1cccd8315-s.p.853070df.woff2",
      "static/media/797e433ab948586e-s.p.dbea232f.woff2"
    ],
    "[project]/app/user/secret-menu/page": [
      "static/media/caa3a2e1cccd8315-s.p.853070df.woff2",
      "static/media/797e433ab948586e-s.p.dbea232f.woff2"
    ],
    "[project]/app/user/settings/page": [
      "static/media/caa3a2e1cccd8315-s.p.853070df.woff2",
      "static/media/797e433ab948586e-s.p.dbea232f.woff2"
    ],
    "[project]/app/verify-pass/page": [
      "static/media/caa3a2e1cccd8315-s.p.853070df.woff2",
      "static/media/797e433ab948586e-s.p.dbea232f.woff2"
    ],
    "[project]/app/waiting-for-pass/page": [
      "static/media/caa3a2e1cccd8315-s.p.853070df.woff2",
      "static/media/797e433ab948586e-s.p.dbea232f.woff2"
    ],
    "[project]/app/wallet-pass/[id]/page": [
      "static/media/caa3a2e1cccd8315-s.p.853070df.woff2",
      "static/media/797e433ab948586e-s.p.dbea232f.woff2"
    ],
    "[project]/app/welcome/page": [
      "static/media/caa3a2e1cccd8315-s.p.853070df.woff2",
      "static/media/797e433ab948586e-s.p.dbea232f.woff2"
    ]
  },
  "appUsingSizeAdjust": true,
  "pages": {},
  "pagesUsingSizeAdjust": false
}